lingva/__init__.py
lingva/extract.py
lingva/polint.py
lingva/extractors/__init__.py
lingva/extractors/babel.py
lingva/extractors/compat.py
lingva/extractors/python.py
lingva/extractors/xml.py
lingva/extractors/zcml.py
lingva-5.0.6.dist-info/licenses/LICENSE
lingva-5.0.6.dist-info/METADATA
lingva-5.0.6.dist-info/WHEEL
lingva-5.0.6.dist-info/entry_points.txt
lingva-5.0.6.dist-info/top_level.txt
lingva-5.0.6.dist-info/RECORD
