Metadata-Version: 2.4
Name: lingva
Version: 5.0.6
Summary: Translation toolset
Author-email: Wichert Akkerman <wichert@wiggy.net>
Maintainer: Arkadii Yakovets, Serhii Murza
License-Expression: BSD-3-Clause
Project-URL: homepage, https://github.com/vacanza/lingva
Project-URL: tracker, https://github.com/vacanza/lingva/issues
Keywords: translation,po,gettext,Babel
Classifier: Intended Audience :: Developers
Classifier: Operating System :: OS Independent
Classifier: Programming Language :: Python :: 3
Classifier: Topic :: Software Development :: Libraries :: Python Modules
License-File: LICENSE
Requires-Dist: click>=8.0.3
Requires-Dist: polib>=1.1.1
Provides-Extra: dev
Requires-Dist: pytest>=8.0.0; extra == "dev"
Requires-Dist: ruff>=0.11.0; extra == "dev"
Provides-Extra: chameleon
Requires-Dist: chameleon; extra == "chameleon"
Dynamic: license-file
